autotypedict/__init__.py
autotypedict-1.0.0.dist-info/LICENSE
autotypedict-1.0.0.dist-info/METADATA
autotypedict-1.0.0.dist-info/WHEEL
autotypedict-1.0.0.dist-info/top_level.txt
autotypedict-1.0.0.dist-info/RECORD
