Metadata-Version: 2.1
Name: autotypedict
Version: 1.0.0
Summary: Dictionary-like class that automatically typecasts string-like values to standard types
Author-email: Bill Hughes <wh@whughes.dev>
Project-URL: Homepage, https://github.com/bhughes339/autotypedict
Project-URL: Bug Tracker, https://github.com/bhughes339/autotypedict/issues
Requires-Python: >=3.8
License-File: LICENSE
